arcanna_mcp/__init__.py
arcanna_mcp/constants.py
arcanna_mcp/environment.py
arcanna_mcp/server.py
arcanna_mcp/models/base_resource.py
arcanna_mcp/models/resource_type.py
arcanna_mcp/tools/__init__.py
arcanna_mcp/tools/custom_code_block.py
arcanna_mcp/tools/events.py
arcanna_mcp/tools/health_check.py
arcanna_mcp/tools/jobs.py
arcanna_mcp/tools/resources.py
arcanna_mcp/utils/__init__.py
arcanna_mcp/utils/exceptions_handler.py
arcanna_mcp/utils/tool_exception_response.py
arcanna_mcp-0.1.0.dist-info/METADATA
arcanna_mcp-0.1.0.dist-info/WHEEL
arcanna_mcp-0.1.0.dist-info/entry_points.txt
arcanna_mcp-0.1.0.dist-info/RECORD
